git_clear_cache/__init__.py
git_clear_cache/core.py
git_clear_cache-0.1.1.dist-info/METADATA
git_clear_cache-0.1.1.dist-info/WHEEL
git_clear_cache-0.1.1.dist-info/entry_points.txt
git_clear_cache-0.1.1.dist-info/top_level.txt
git_clear_cache-0.1.1.dist-info/RECORD
