Metadata-Version: 2.4
Name: git-clear-cache
Version: 0.1.1
Home-page: https://github.com/MagIlyasDOMA/git-clear-cache
Author: Маг Ильяс DOMA
Author-email: magilyas.doma.09@list.ru
License: MIT
Classifier: Development Status :: 3 - Alpha
Classifier: Intended Audience :: Developers
Classifier: Programming Language :: Python :: 3
Classifier: Programming Language :: Python :: 3.6
Classifier: Programming Language :: Python :: 3.7
Classifier: Programming Language :: Python :: 3.8
Classifier: Programming Language :: Python :: 3.9
Classifier: Programming Language :: Python :: 3.10
Classifier: Programming Language :: Python :: 3.11
Classifier: Programming Language :: Python :: 3.12
Classifier: Programming Language :: Python :: 3.13
Classifier: Programming Language :: Python :: 3.14
Classifier: Programming Language :: Python :: 3 :: Only
Requires-Dist: GitPython>=3.1.45
Requires-Dist: python-dotenv>=1.2.1
Requires-Dist: undefined-python
Dynamic: author
Dynamic: author-email
Dynamic: classifier
Dynamic: home-page
Dynamic: license
Dynamic: requires-dist
